chimeric/__init__.py
chimeric/base.py
chimeric/chimeric.py
chimeric/exceptions.py
chimeric/py.typed
chimeric/tools.py
chimeric/types.py
chimeric/utils.py
chimeric/providers/__init__.py
chimeric/providers/anthropic/__init__.py
chimeric/providers/anthropic/client.py
chimeric/providers/cerebras/__init__.py
chimeric/providers/cerebras/client.py
chimeric/providers/cohere/__init__.py
chimeric/providers/cohere/client.py
chimeric/providers/google/__init__.py
chimeric/providers/google/client.py
chimeric/providers/grok/__init__.py
chimeric/providers/grok/client.py
chimeric/providers/groq/__init__.py
chimeric/providers/groq/client.py
chimeric/providers/openai/__init__.py
chimeric/providers/openai/client.py
chimeric-0.1.0.dist-info/METADATA
chimeric-0.1.0.dist-info/WHEEL
chimeric-0.1.0.dist-info/licenses/LICENSE
chimeric-0.1.0.dist-info/RECORD
