Metadata-Version: 2.4
Name: chimeric
Version: 0.1.0
Summary: Unified interface for multiple LLM providers with automatic provider detection and seamless switching
Project-URL: Repository, https://github.com/Verdenroz/chimeric
Project-URL: Issues, https://github.com/Verdenroz/chimeric/issues
Project-URL: Documentation, https://verdenroz.github.io/chimeric/
Project-URL: Changelog, https://github.com/Verdenroz/chimeric/blob/main/CHANGELOG.md
Author-email: Harvey Tseng <harveytseng2@gmail.com>
License: MIT
License-File: LICENSE
Keywords: ai,anthropic,gemini,llm,multi-provider,openai,unified-interface
Classifier: Development Status :: 4 - Beta
Classifier: Intended Audience :: Developers
Classifier: License :: OSI Approved :: MIT License
Classifier: Operating System :: OS Independent
Classifier: Programming Language :: Python
Classifier: Programming Language :: Python :: 3
Classifier: Programming Language :: Python :: 3.11
Classifier: Programming Language :: Python :: 3.12
Classifier: Programming Language :: Python :: 3.13
Classifier: Topic :: Scientific/Engineering :: Artificial Intelligence
Classifier: Topic :: Software Development :: Libraries :: Python Modules
Classifier: Typing :: Typed
Requires-Python: <4.0,>=3.11
Requires-Dist: pydantic>=2.11.5
Provides-Extra: all
Requires-Dist: anthropic>=0.52.2; extra == 'all'
Requires-Dist: cerebras-cloud-sdk>=1.35.0; extra == 'all'
Requires-Dist: cohere>=5.15.0; extra == 'all'
Requires-Dist: google-genai>=1.2.0; extra == 'all'
Requires-Dist: groq>=0.4.0; extra == 'all'
Requires-Dist: openai>=1.84.0; extra == 'all'
Requires-Dist: xai-sdk>=1.0.0; extra == 'all'
Provides-Extra: anthropic
Requires-Dist: anthropic>=0.52.2; extra == 'anthropic'
Provides-Extra: cerebras
Requires-Dist: cerebras-cloud-sdk>=1.35.0; extra == 'cerebras'
Provides-Extra: cohere
Requires-Dist: cohere>=5.15.0; extra == 'cohere'
Provides-Extra: google
Requires-Dist: google-genai>=1.2.0; extra == 'google'
Provides-Extra: grok
Requires-Dist: xai-sdk>=1.0.0; extra == 'grok'
Provides-Extra: groq
Requires-Dist: groq>=0.4.0; extra == 'groq'
Provides-Extra: openai
Requires-Dist: openai>=1.84.0; extra == 'openai'
